scryr/__init__.py
scryr/analyzer.py
scryr/cli.py
scryr/renderer.py
scryr/scanner.py
scryr-0.1.1.dist-info/METADATA
scryr-0.1.1.dist-info/WHEEL
scryr-0.1.1.dist-info/entry_points.txt
scryr-0.1.1.dist-info/licenses/LICENSE
scryr-0.1.1.dist-info/RECORD
