Metadata-Version: 2.4
Name: scryr
Version: 0.1.1
Summary: A minimal tool that maps project structure and intent
Project-URL: Homepage, https://github.com/Prajwal-Pujari/scryr.git
Project-URL: Repository, https://github.com/Prajwal-Pujari/scryr.git
Author-email: Prajwal <imprajwal793@gmail.com>
License: MIT
License-File: LICENSE
Keywords: cli,mapping,project,structure,tree
Classifier: Development Status :: 4 - Beta
Classifier: Intended Audience :: Developers
Classifier: License :: OSI Approved :: MIT License
Classifier: Programming Language :: Python :: 3
Classifier: Programming Language :: Python :: 3.9
Classifier: Programming Language :: Python :: 3.10
Classifier: Programming Language :: Python :: 3.11
Classifier: Programming Language :: Python :: 3.12
Requires-Python: >=3.9
Requires-Dist: rich>=13.0.0
